CHANGES.txt
LICENSE.txt
MANIFEST.in
README.txt
bootstrap.py
setup.py
src/p01/__init__.py
src/p01.secureprincipal.egg-info/PKG-INFO
src/p01.secureprincipal.egg-info/SOURCES.txt
src/p01.secureprincipal.egg-info/dependency_links.txt
src/p01.secureprincipal.egg-info/namespace_packages.txt
src/p01.secureprincipal.egg-info/not-zip-safe
src/p01.secureprincipal.egg-info/requires.txt
src/p01.secureprincipal.egg-info/top_level.txt
src/p01/secureprincipal/README.txt
src/p01/secureprincipal/__init__.py
src/p01/secureprincipal/configure.zcml
src/p01/secureprincipal/interfaces.py
src/p01/secureprincipal/policy.py
src/p01/secureprincipal/principal.py
src/p01/secureprincipal/tests.py