Metadata-Version: 1.0
Name: p01.secureprincipal
Version: 0.5.0
Summary: Principal based securitypolicy for Zope3 using built in security declarations
Home-page: http://cheeseshop.python.org/pypi/p01.secureprincipal
Author: Roger Ineichen, Projekt01 GmbH
Author-email: dev@projekt01.ch
License: ZPL 2.1
Keywords: P01 securitypolicy roles principal Zope3
Platform: UNKNOWN
Classifier: Development Status :: 4 - Beta
Classifier: Environment :: Web Environment
Classifier: Intended Audience :: Developers
Classifier: License :: OSI Approved :: Zope Public License
Classifier: Programming Language :: Python
Classifier: Natural Language :: English
Classifier: Operating System :: OS Independent
Classifier: Topic :: Internet :: WWW/HTTP
Classifier: Framework :: Zope3
